[
  {
    "keyword": "기계식 키보드 추천",
    "title": "기계식 키보드 추천, 뭘 사야 후회 안 할까?",
    "tags": [
      "기계식키보드",
      "키보드추천",
      "게이밍키보드",
      "무선키보드",
      "유선키보드",
      "큐센키보드",
      "에이투키보드"
    ],
    "file": "output\\it-posts\\2026-03-25\\tool_1_기계식_키보드_추천.html"
  },
  {
    "keyword": "그래픽카드 비교",
    "title": "그래픽카드, 뭘 사야 후회 안 할까? 3종 비교",
    "tags": [
      "그래픽카드",
      "GTX1070",
      "RTX2060",
      "그래픽카드지지대",
      "쿠팡추천",
      "게이밍PC",
      "IT리뷰"
    ],
    "file": "output\\it-posts\\2026-03-25\\tool_2_그래픽카드_비교.html"
  },
  {
    "keyword": "스마트폰 저장 공간 확보법",
    "title": "스마트폰 저장 공간, 뭘 해야 후회 안 할까?",
    "tags": [],
    "file": "output\\it-posts\\2026-03-25\\tool_3_스마트폰_저장_공간_확보법.html"
  }
]